{
  "items": [
    {
      "name": "Wheel",
      "boxes_xyxy": [
        [
          800.5625,
          483.744140625,
          1141.25,
          751.5
        ],
        [
          41.75,
          480.75,
          322.5,
          663.0
        ],
        [
          38.875,
          358.75,
          316.5,
          589.25
        ],
        [
          805.0,
          481.947265625,
          940.5,
          757.0
        ],
        [
          772.8671875,
          437.75,
          1134.25,
          587.0
        ]
      ],
      "scores": [
        0.5116403698921204,
        0.4366220533847809,
        0.39303550124168396,
        0.33361175656318665,
        0.32885265350341797
      ],
      "mask_path": "./owl_sam_out/wheel_mask.png"
    },
    {
      "name": "Fuel Tank",
      "boxes_xyxy": [
        [
          332.25,
          214.8125,
          515.5,
          362.25
        ],
        [
          344.041015625,
          175.5,
          655.75,
          319.25
        ],
        [
          283.0,
          480.921875,
          332.0,
          542.0625
        ],
        [
          409.75,
          500.234375,
          722.0,
          702.125
        ],
        [
          776.109375,
          341.875,
          1189.75,
          476.5
        ]
      ],
      "scores": [
        0.8077641129493713,
        0.7730450630187988,
        0.5678167343139648,
        0.5395594835281372,
        0.4405294358730316
      ],
      "mask_path": "./owl_sam_out/fuel_tank_mask.png"
    },
    {
      "name": "Engine",
      "boxes_xyxy": [
        [
          354.5,
          351.0,
          515.0,
          582.5
        ]
      ],
      "scores": [
        0.5868780016899109
      ],
      "mask_path": "./owl_sam_out/engine_mask.png"
    },
    {
      "name": "Exhaust Pipe",
      "boxes_xyxy": [
        [
          775.05078125,
          447.25,
          951.875,
          586.0
        ],
        [
          348.0,
          630.375,
          423.0,
          692.625
        ]
      ],
      "scores": [
        0.38543248176574707,
        0.3069423735141754
      ],
      "mask_path": "./owl_sam_out/exhaust_pipe_mask.png"
    },
    {
      "name": "Seat",
      "boxes_xyxy": [
        [
          634.25,
          307.25,
          935.5,
          448.375
        ]
      ],
      "scores": [
        0.2952299118041992
      ],
      "mask_path": "./owl_sam_out/seat_mask.png"
    },
    {
      "name": "Foot Pegs",
      "boxes_xyxy": [
        [
          125.125,
          480.828125,
          221.875,
          544.5625
        ],
        [
          175.875,
          481.53125,
          222.625,
          539.875
        ],
        [
          1149.25,
          481.951171875,
          1180.25,
          516.25
        ],
        [
          424.5,
          639.0,
          514.0,
          687.5
        ]
      ],
      "scores": [
        0.24256430566310883,
        0.24184732139110565,
        0.2312668114900589,
        0.22354651987552643
      ],
      "mask_path": "./owl_sam_out/foot_pegs_mask.png"
    },
    {
      "name": "Handlebar",
      "boxes_xyxy": [
        [
          236.125,
          117.4375,
          343.0,
          153.5
        ],
        [
          238.875,
          101.875,
          514.0,
          164.875
        ],
        [
          429.5,
          132.125,
          512.0,
          167.375
        ],
        [
          375.25,
          117.375,
          513.5,
          167.875
        ],
        [
          343.5302734375,
          96.625,
          519.5,
          224.875
        ]
      ],
      "scores": [
        0.4372827410697937,
        0.4360816180706024,
        0.430865615606308,
        0.3538746237754822,
        0.34654128551483154
      ],
      "mask_path": "./owl_sam_out/handlebar_mask.png"
    },
    {
      "name": "Mirror",
      "boxes_xyxy": [],
      "scores": [],
      "mask_path": null
    },
    {
      "name": "Headlight",
      "boxes_xyxy": [
        [
          1084.5,
          415.125,
          1132.25,
          455.25
        ],
        [
          468.0625,
          96.1875,
          508.625,
          141.5
        ]
      ],
      "scores": [
        0.3349156677722931,
        0.3182732164859772
      ],
      "mask_path": "./owl_sam_out/headlight_mask.png"
    }
  ]
}